{
  "generatedAt": "2026-06-05T16:36:38.117Z",
  "agentCostRatio": 0.58,
  "calculations": [
    {
      "dealId": "16874",
      "updatedAt": "2026-06-02T20:08:54.127Z",
      "positions": []
    },
    {
      "dealId": "16888",
      "updatedAt": "2026-06-05T16:36:37.259Z",
      "positions": [
        {
          "id": "85de400a-3bec-4e52-b85f-b476fe2a4ebe",
          "catalogId": "materials-клеи-очистители-очиститель-космофен-5-cosmo-cl-3-2068",
          "qty": 2,
          "unit": "шт",
          "unitCost": 1443,
          "section": "materials",
          "title": "Клеи, очистители Очиститель Космофен 5 (Cosmo CL-300.110) 1 литр",
          "calcMode": "pieces",
          "note": "Прайс по материалам.xlsx; строка 1446; столбец G"
        },
        {
          "id": "f2cd1d73-0cb2-4a4e-ae91-29681c3ad51d",
          "catalogId": "materials-бумага-транслюцентная-vilaseca-skylight-150-1-29-1934",
          "qty": 0,
          "unit": "м2",
          "unitCost": 75.67,
          "section": "materials",
          "title": "Бумага транслюцентная Vilaseca Skylight 150 (1,29х100)",
          "calcMode": "area",
          "note": "Прайс по материалам.xlsx; строка 1283; столбец G"
        }
      ]
    }
  ]
}
